bomail/__init__.py
bomail/bomail.py
bomail/cli/__init__.py
bomail/cli/check_sched.py
bomail/cli/chstate.py
bomail/cli/compose.py
bomail/cli/gui.py
bomail/cli/mailfile.py
bomail/cli/meta.py
bomail/cli/process.py
bomail/cli/search.py
bomail/cli/send.py
bomail/cli/stats.py
bomail/config/__init__.py
bomail/config/conf_setup.py
bomail/config/conf_strs.py
bomail/config/config.py
bomail/config/edit_config.py
bomail/config/guiconfig.py
bomail/config/optconfig.py
bomail/config/pathconfig.py
bomail/config/sendconfig.py
bomail/guistuff/__init__.py
bomail/guistuff/acts.py
bomail/guistuff/display.py
bomail/guistuff/display_fmt.py
bomail/guistuff/get_txt.py
bomail/guistuff/gui_util.py
bomail/guistuff/mygui.py
bomail/guistuff/old_tabthreadview.py
bomail/guistuff/tabnothread.py
bomail/guistuff/tabthread.py
bomail/guistuff/threadreader.py
bomail/guistuff/viewinterface.py
bomail/util/__init__.py
bomail/util/addr.py
bomail/util/attach.py
bomail/util/datestuff.py
bomail/util/handle.py
bomail/util/listmail.py
bomail/util/merge_lines.py
bomail/util/mime_to_mailfile.py
bomail/util/msgids.py
bomail/util/remove_lines.py
bomail/util/search_opts.py
bomail/util/tags.py
bomail/util/thread.py
bomail/util/unpack_attach.py
bomail/util/util.py
bomail-0.9.4.1.dist-info/METADATA
bomail-0.9.4.1.dist-info/WHEEL
bomail-0.9.4.1.dist-info/entry_points.txt
bomail-0.9.4.1.dist-info/top_level.txt
bomail-0.9.4.1.dist-info/RECORD
