Metadata-Version: 2.1
Name: bomail
Version: 0.9.4.1
Summary: A homemade, hobbyist, hacky system for organizing and interacting with email.
Home-page: https://bitbucket.org/bowaggonerpublic/bomail
Author: Bo Waggoner
Author-email: luv2runxc@gmail.com
License: UNKNOWN
Platform: UNKNOWN
Requires-Python: >=3.5
Requires-Dist: datetime
Requires-Dist: python-dateutil
